nonebot_plugin_chikari_yinpa/__init__.py
nonebot_plugin_chikari_yinpa/config.py
nonebot_plugin_chikari_yinpa/data_handles.py
nonebot_plugin_chikari_yinpa/dicts.py
nonebot_plugin_chikari_yinpa/handles.py
nonebot_plugin_chikari_yinpa/utils.py
nonebot_plugin_chikari_yinpa-1.4.3.dist-info/LICENSE
nonebot_plugin_chikari_yinpa-1.4.3.dist-info/METADATA
nonebot_plugin_chikari_yinpa-1.4.3.dist-info/WHEEL
nonebot_plugin_chikari_yinpa-1.4.3.dist-info/top_level.txt
nonebot_plugin_chikari_yinpa-1.4.3.dist-info/RECORD
